[{"id":1,"name":"Evángelos Odysséas Papathanassíou","birthDate":"29/3/1943","userName":"Vintage Synths","email":"vintagesynths@vs.com","password":"vint1234","phone":2224444,"avatar":"vangelis.jpg","location":"Athens","country":"GRK","rating":4},{"id":2,"name":"Joe Bonamassa","birthDate":"8/5/1977","userName":"Joe's Bazaar","email":"joes@bazaar.com","password":"joes1234","phone":7655433,"avatar":"joes-bazaar.jpg","location":"California","country":"US","rating":4.5},{"id":3,"name":"Edgar Froese","birthDate":"6/6/1944","userName":"Promusik","email":"promusikgmbh@orange.de","password":"prom1234","phone":1115563,"avatar":"edgar-froese.jpg","location":"Viena","country":"AU","rating":4.6},{"id":4,"name":"Gustavo Cerati","birthDate":"1959-08-11","userName":"soda-stereo","email":"soda@graciastotales.com","password":["Elrito123","Elrito123"],"phone":"45444944","avatar":"","location":"Calle Falsa 123","country":"Argentina","rating":0}]